{
    "BIN_FCSKU_DATA": {
        "B001ETR7CK": {
            "asin": "B001ETR7CK",
            "height": {
                "unit": "IN",
                "value": 1.0999999988780003
            },
            "length": {
                "unit": "IN",
                "value": 3.6999999962260004
            },
            "name": "Stalwart Sprinkler Head Hide-a-Key",
            "normalizedName": "Stalwart Sprinkler Head Hide-a-Key",
            "quantity": 1,
            "weight": {
                "unit": "pounds",
                "value": 0.10000000000000002
            },
            "width": {
                "unit": "IN",
                "value": 1.599999998368
            }
        },
        "B002HJ916G": {
            "asin": "B002HJ916G",
            "height": {
                "unit": "IN",
                "value": 0.799999999184
            },
            "length": {
                "unit": "IN",
                "value": 5.599999994287999
            },
            "name": "Korsteel Long Neck Dressage Spurs",
            "normalizedName": "Korsteel Long Neck Dressage Spurs",
            "quantity": 1,
            "weight": {
                "unit": "pounds",
                "value": 0.20000000000000004
            },
            "width": {
                "unit": "IN",
                "value": 5.099999994798
            }
        },
        "B003MYA66E": {
            "asin": "B003MYA66E",
            "height": {
                "unit": "IN",
                "value": 1.0999999988780003
            },
            "length": {
                "unit": "IN",
                "value": 4.9999999949
            },
            "name": "Jp Korsteel Loose Ring Snaffle - 5",
            "normalizedName": "Jp Korsteel Loose Ring Snaffle - 5",
            "quantity": 1,
            "weight": {
                "unit": "pounds",
                "value": 0.3499999997064932
            },
            "width": {
                "unit": "IN",
                "value": 4.899999995002001
            }
        },
        "B004DI0LQ8": {
            "asin": "B004DI0LQ8",
            "height": {
                "unit": "IN",
                "value": 2.399999997552
            },
            "length": {
                "unit": "IN",
                "value": 5.799999994084
            },
            "name": "Mentos Rolls, Cinnamon, 1.32 Ounce (Pack of 15)",
            "normalizedName": "(Pack of 15) Mentos Rolls, Cinnamon, 1.32 Ounce",
            "quantity": 2,
            "weight": {
                "unit": "pounds",
                "value": 1.35
            },
            "width": {
                "unit": "IN",
                "value": 3.99999999592
            }
        },
        "B01C297Z2W": {
            "asin": "B01C297Z2W",
            "height": {
                "unit": "IN",
                "value": 2.1999999977560005
            },
            "length": {
                "unit": "IN",
                "value": 6.399999993472
            },
            "name": "The Ultimate Concealed Carry CCW Leather Gun Belt - Lifetime Warranty - 2016 Model - New and Improved - 14 ounce 1 1/2 inch Premium Full Grain Leather Belt - Handmade in the USA! Brown Size 42",
            "normalizedName": "The Ultimate Concealed Carry CCW Leather Gun Belt - Lifetime Warranty - 2016 Model - New and Improved - 14 ounce 1 1/2 inch Premium Full Grain Leather Belt - Handmade in the USA! Brown Size 42",
            "quantity": 1,
            "weight": {
                "unit": "pounds",
                "value": 0.8299999993039698
            },
            "width": {
                "unit": "IN",
                "value": 6.099999993778
            }
        }
    },
    "EXPECTED_QUANTITY": 6
}